{"code":0,"message":"success","data":{"id":199,"nickName":"🔥___sarmili___🔥","avatar":"https://data.flintapp.net/199/public/8.webp","banner":"https://data.flintapp.net/199/public/13.webp","cover":"https://data.flintapp.net/199/public/8.webp","age":29,"gender":"Female","slogan":"","albums":[{"url":"https://data.flintapp.net/199/public/8.webp","thumbnail":"https://data.flintapp.net/199/public/8_thumbnail.webp"}],"privateAlbums":[{"url":"https://data.flintapp.net/199/private/5.webp","thumbnail":"https://data.flintapp.net/199/private/5_thumbnail.webp"}],"isVIP":false,"vipExpiredTime":0,"tags":["Board games","Role-playing games","Shooter games","Strategy games","Video games","Action movies","Musical theatre","Science fiction movies","Blues music","Pop music","Newspapers","TV comedies","Distilled beverage","Japanese cuisine","Desserts","Painting","Photography","Reptiles","Military","Politics","Adventure travel","Hybrids","Hair products","Handbags","biking","Soccer"],"viewCount":400}}
