{"code":0,"message":"success","data":{"id":242,"nickName":"rani rani111","avatar":"https://data.flintapp.net/242/public/7.webp","banner":"https://data.flintapp.net/242/public/7.webp","cover":"https://data.flintapp.net/242/public/7.webp","age":20,"gender":"Female","slogan":"","albums":[{"url":"https://data.flintapp.net/242/public/7.webp","thumbnail":"https://data.flintapp.net/242/public/7_thumbnail.webp"},{"url":"https://data.flintapp.net/242/public/1.webp","thumbnail":"https://data.flintapp.net/242/public/1_thumbnail.webp"}],"privateAlbums":[{"url":"https://data.flintapp.net/242/private/14.webp","thumbnail":"https://data.flintapp.net/242/private/14_thumbnail.webp"},{"url":"https://data.flintapp.net/242/private/30.webp","thumbnail":"https://data.flintapp.net/242/private/30_thumbnail.webp"}],"isVIP":false,"vipExpiredTime":0,"tags":["Sports games","Word games","Bars","Rhythm and blues music","Comics","Newspapers","Soft drinks","Fine art","Do it yourself (DIY)","Pet food","Tourism","Minivans","Motorcycles","Trucks","Camping"],"viewCount":435}}
